CA.py-1.8.1.data/scripts/ca.py
certificator/__init__.py
certificator/ca.py
certificator/openssl_util.py
CA.py-1.8.1.dist-info/LICENSE
CA.py-1.8.1.dist-info/METADATA
CA.py-1.8.1.dist-info/WHEEL
CA.py-1.8.1.dist-info/top_level.txt
CA.py-1.8.1.dist-info/RECORD
