Metadata-Version: 2.1
Name: CA.py
Version: 1.8.1
Summary: CA.pl Python Fork
Home-page: https://github.com/search5/ca.py
Author: Lee Ji-Ho
Author-email: search5@gmail.com
License: Apache License 2.0
Download-URL: https://github.com/search5/ca.py/tarball/1.8.1
Keywords: openssl,ca,cert
Platform: any
Classifier: Development Status :: 4 - Beta
Classifier: Environment :: Console
Classifier: License :: OSI Approved :: Apache Software License
Classifier: Operating System :: POSIX :: Linux
Classifier: Operating System :: MacOS :: MacOS X
Classifier: Operating System :: Microsoft :: Windows :: Windows 7
Classifier: Programming Language :: Python
Classifier: Programming Language :: Python :: 3.3
Classifier: Programming Language :: Python :: 3.4
Classifier: Programming Language :: Python :: 3.5
Classifier: Programming Language :: Python :: 3.6
Classifier: Topic :: System :: Networking
Classifier: Topic :: Security :: Cryptography
Requires-Dist: configobj (==5.0.6)
Requires-Dist: click
